relaymcp/__init__.py
relaymcp/main.py
relaymcp/config/models.py
relaymcp-0.0.1.dist-info/METADATA
relaymcp-0.0.1.dist-info/WHEEL
relaymcp-0.0.1.dist-info/entry_points.txt
relaymcp-0.0.1.dist-info/RECORD
