Metadata-Version: 2.4
Name: relaymcp
Version: 0.0.1
Summary: Add your description here
Author-email: TerminalMan <84923604+SecretiveShell@users.noreply.github.com>
Requires-Python: >=3.10
Requires-Dist: fastapi>=0.115.12
Requires-Dist: mcp>=1.6.0
Requires-Dist: uvicorn>=0.34.0
